Metadata-Version: 2.1
Name: slovo
Version: 2020.3.25
Summary: Making words
Home-page: https://github.com/butuzov/slovo
Author: Oleg Butuzov
Author-email: butuzov@made.ua
License: Apache License 2.0
Keywords: words,dictionalies
Platform: OS Independent
Classifier: Development Status :: 2 - Pre-Alpha
Classifier: Intended Audience :: Education
Classifier: License :: OSI Approved :: Apache Software License
Classifier: Topic :: Education
Classifier: Programming Language :: Python :: 3.6
Classifier: Programming Language :: Python :: 3.7
Classifier: Programming Language :: Python :: 3.8
Requires-Python: >=3.6
